enterprise/__init__.py
enterprise/apps/__init__.py
enterprise/apps/authentication/__init__.py
enterprise/apps/authentication/admin.py
enterprise/apps/authentication/apps.py
enterprise/apps/authentication/models.py
enterprise/apps/authentication/tests.py
enterprise/apps/authentication/urls.py
enterprise/apps/authentication/views.py
enterprise/apps/authentication/migrations/__init__.py
enterprise/apps/superuser/__init__.py
enterprise/apps/superuser/admin.py
enterprise/apps/superuser/apps.py
enterprise/apps/superuser/forms.py
enterprise/apps/superuser/models.py
enterprise/apps/superuser/tests.py
enterprise/apps/superuser/urls.py
enterprise/apps/superuser/migrations/__init__.py
enterprise/apps/superuser/views/__init__.py
enterprise/apps/superuser/views/group.py
enterprise/apps/superuser/views/permission.py
enterprise/apps/superuser/views/user.py
enterprise/apps/tracker/__init__.py
enterprise/apps/tracker/apps.py
enterprise/apps/tracker/tests.py
enterprise/apps/tracker/urls.py
enterprise/apps/tracker/views/__init__.py
enterprise/apps/tracker/views/raw.py
enterprise/libs/__init__.py
enterprise/libs/base36.py
enterprise/libs/base62.py
enterprise/libs/brand.py
enterprise/libs/decimal_lib.py
enterprise/libs/email.py
enterprise/libs/form.py
enterprise/libs/ip_address.py
enterprise/libs/json_response.py
enterprise/libs/model.py
enterprise/libs/moment.py
enterprise/libs/nonce.py
enterprise/libs/otp.py
enterprise/libs/pay_constants.py
enterprise/libs/rackspace_cloud_files.py
enterprise/libs/storage.py
enterprise/libs/payment/__init__.py
enterprise/libs/payment/midtrans.py
enterprise/libs/payment/wallet.py
enterprise/libs/payment/xendit.py
enterprise/libs/rest_module/__init__.py
enterprise/libs/rest_module/authentication.py
enterprise/libs/rest_module/permission.py
enterprise/libs/rest_module/search.py
enterprise/libs/rest_module/serializer.py
enterprise/libs/rest_module/viewset.py
enterprise/libs/view/__init__.py
enterprise/libs/view/form.py
enterprise/libs/view/tracker.py
enterprise-0.4.2.dist-info/LICENSE
enterprise-0.4.2.dist-info/METADATA
enterprise-0.4.2.dist-info/WHEEL
enterprise-0.4.2.dist-info/top_level.txt
enterprise-0.4.2.dist-info/RECORD
