Metadata-Version: 2.1
Name: enterprise
Version: 0.4.2
Summary: A bunch of libraries for building backend enterprise on django
Home-page: https://github.com/ardzix/django-enterprise-core
Author: Arif Dzikrullah
Author-email: ardzix@hotmail.com
License: GPL 3.0
Keywords: enterprise,backend,admin,crud,django
Platform: UNKNOWN
Classifier: Development Status :: 4 - Beta
Classifier: Intended Audience :: Developers
Classifier: Topic :: Software Development :: Build Tools
Classifier: License :: OSI Approved :: GNU General Public License v3 (GPLv3)
Classifier: Programming Language :: Python :: 3
Requires-Dist: Django (==2.2.13)
Requires-Dist: djangorestframework (==3.9.1)
Requires-Dist: timeago (==1.0.8)
Requires-Dist: psycopg2 (==2.7.5)
Requires-Dist: postgis (==1.0.4)
Requires-Dist: arrow (==0.12.1)
Requires-Dist: pycountry (==17.5.14)
Requires-Dist: rackspacesdk (==0.7.5)
Requires-Dist: openstacksdk (==0.17.2)
Requires-Dist: PyJWT (==1.7.1)
